cbtool/__init__.py
cbtool/setup.py
cbtool/lib/__init__.py
cbtool/lib/api/__init__.py
cbtool/lib/api/api_service.py
cbtool/lib/api/api_service_client.py
cbtool/lib/auxiliary/__init__.py
cbtool/lib/auxiliary/cli.py
cbtool/lib/auxiliary/code_instrumentation.py
cbtool/lib/auxiliary/config.py
cbtool/lib/auxiliary/data_ops.py
cbtool/lib/auxiliary/dependencies.py
cbtool/lib/auxiliary/gui.py
cbtool/lib/auxiliary/thread_pool.py
cbtool/lib/auxiliary/value_generation.py
cbtool/lib/clouds/__init__.py
cbtool/lib/clouds/as_cloud_ops.py
cbtool/lib/clouds/csk_cloud_ops.py
cbtool/lib/clouds/do_cloud_ops.py
cbtool/lib/clouds/dok8s_cloud_ops.py
cbtool/lib/clouds/ec2_cloud_ops.py
cbtool/lib/clouds/gce_cloud_ops.py
cbtool/lib/clouds/kub_cloud_ops.py
cbtool/lib/clouds/libcloud_common.py
cbtool/lib/clouds/nop_cloud_ops.py
cbtool/lib/clouds/os_cloud_ops.py
cbtool/lib/clouds/osk_cloud_ops.py
cbtool/lib/clouds/pcm_cloud_ops.py
cbtool/lib/clouds/pdm_cloud_ops.py
cbtool/lib/clouds/plm_cloud_ops.py
cbtool/lib/clouds/shared_functions.py
cbtool/lib/clouds/sim_cloud_ops.py
cbtool/lib/clouds/slr_cloud_ops.py
cbtool/lib/clouds/vcd_cloud_ops.py
cbtool/lib/clouds/zsk_cloud_ops.py
cbtool/lib/operations/__init__.py
cbtool/lib/operations/active_operations.py
cbtool/lib/operations/base_operations.py
cbtool/lib/operations/passive_operations.py
cbtool/lib/remote/__init__.py
cbtool/lib/remote/hotplug_rem_ops.py
cbtool/lib/remote/network_functions.py
cbtool/lib/remote/process_management.py
cbtool/lib/remote/ssh_ops.py
cbtool/lib/stores/__init__.py
cbtool/lib/stores/common_datastore_adapter.py
cbtool/lib/stores/mongodb_datastore_adapter.py
cbtool/lib/stores/mysql_datastore_adapter.py
cbtool/lib/stores/redis_datastore_adapter.py
cbtool/lib/stores/stores_initial_setup.py
cbtool-3.0.5.dist-info/DESCRIPTION.rst
cbtool-3.0.5.dist-info/METADATA
cbtool-3.0.5.dist-info/RECORD
cbtool-3.0.5.dist-info/WHEEL
cbtool-3.0.5.dist-info/metadata.json
cbtool-3.0.5.dist-info/top_level.txt
