Metadata-Version: 2.0
Name: cbtool
Version: 3.0.5
Summary: CloudBench: Cloud Rapid Experimentation and Analysis Toolkit
Home-page: https://github.com/ibmcb/cbtool
Author: Marcio Silva, Michael Galaxy
Author-email: cbtool-admin@googlegroups.com
License: UNKNOWN
Download-URL: https://github.com/ibmcb/cbtool/archive/3.0.tar.gz
Keywords: cloudbench,cloud,benchmarking,spec
Platform: UNKNOWN
Classifier: Development Status :: 5 - Production/Stable
Classifier: Intended Audience :: Developers
Classifier: Topic :: Software Development :: Build Tools
Classifier: License :: OSI Approved :: Apache Software License
Classifier: Programming Language :: Python :: 3.6
Requires-Python: >=3.6
Requires-Dist: prettytable
Requires-Dist: python-daemon
Requires-Dist: twisted
Requires-Dist: webob
Requires-Dist: beaker
Requires-Dist: python-redis
Requires-Dist: pymongo
Requires-Dist: pypureomapi
Requires-Dist: python-novaclient
Requires-Dist: python-neutronclient
Requires-Dist: python-cinderclient
Requires-Dist: python-glanceclient
Requires-Dist: softlayer
Requires-Dist: boto
Requires-Dist: apache-libcloud
Requires-Dist: docker
Requires-Dist: pylxd
Requires-Dist: pykube
Requires-Dist: docutils
Requires-Dist: markup
Requires-Dist: pyyaml
Requires-Dist: ruamel-yaml
Requires-Dist: urllib3
Requires-Dist: httplib2shim
Requires-Dist: python-dateutil
Requires-Dist: pillow
Requires-Dist: jsonschema
Requires-Dist: mysql-connector
Requires-Dist: distro
